<?xml version="1.0" encoding='UTF-8'?>
<!DOCTYPE hibernate-mapping PUBLIC
"-//Hibernate/Hibernate Mapping DTD 3.0//EN"
"http://hibernate.sourceforge.net/hibernate-mapping-3.0.dtd" >
<!-- Mapping file autogenerated by MyEclipse Persistence Tools-->

<hibernate-mapping>
	<class name="cose.seu.entity.History" table="ScanHistory">
		<id name="SID" type="java.lang.Long" column="SID">
		
		<generator class="native"/>
		</id>
		
		<property name="HisDate" type="java.util.Date" column="SCADATE"></property>
		
		<many-to-one name="user" class="cose.seu.entity.UserInfo" column="USERID">
		</many-to-one>
		<many-to-one name="book" class="cose.seu.entity.Book" column="BID">
		</many-to-one>
		
	</class>
</hibernate-mapping>